aiowowapi/__init__.py
aiowowapi/api.py
aiowowapi/py.typed
aiowowapi/regions.py
aiowowapi/wowapi.py
aiowowapi/classic/__init__.py
aiowowapi/classic/classic.py
aiowowapi/classic/game_data_classic.py
aiowowapi/classic/py.typed
aiowowapi/retail/__init__.py
aiowowapi/retail/game_data.py
aiowowapi/retail/profile.py
aiowowapi/retail/py.typed
aiowowapi/retail/retail.py
aiowowapi-2.1.5.dist-info/LICENSE
aiowowapi-2.1.5.dist-info/METADATA
aiowowapi-2.1.5.dist-info/WHEEL
aiowowapi-2.1.5.dist-info/top_level.txt
aiowowapi-2.1.5.dist-info/RECORD
