Metadata-Version: 2.1
Name: aiowowapi
Version: 2.1.5
Summary: An asynchronous Python wrapper for the World of Warcraft APIs.
Home-page: https://github.com/Adalyia/aiowowapi
Author: Adalyia
License: MIT
Keywords: wow,world of warcraft,api,wrapper,asynchronous,async,battle.net,blizzard
Classifier: Development Status :: 5 - Production/Stable
Classifier: License :: OSI Approved :: MIT License
Classifier: Intended Audience :: Developers
Classifier: Natural Language :: English
Classifier: Operating System :: OS Independent
Classifier: Programming Language :: Python :: 3
Classifier: Programming Language :: Python :: 3.8
Classifier: Programming Language :: Python :: 3.9
Classifier: Programming Language :: Python :: 3.10
Classifier: Programming Language :: Python :: 3.11
Classifier: Topic :: Games/Entertainment
Classifier: Topic :: Software Development :: Libraries
Classifier: Topic :: Software Development :: Libraries :: Python Modules
Classifier: Typing :: Typed
Requires-Python: >=3.8
License-File: LICENSE
Requires-Dist: aiohttp >=3.8.0
Provides-Extra: docs
Requires-Dist: sphinx >=4.1.2 ; extra == 'docs'
Requires-Dist: sphinx-rtd-theme >=1.0.0 ; extra == 'docs'
Provides-Extra: testing
Requires-Dist: pytest >=6.2.4 ; extra == 'testing'
Requires-Dist: pytest-asyncio >=0.15.1 ; extra == 'testing'
Requires-Dist: flake8 >=5.0.4 ; extra == 'testing'
Requires-Dist: mypy >=0.975 ; extra == 'testing'
